rayvision_katana/Analyse.py
rayvision_katana/__init__.py
rayvision_katana/analyse_katana.py
rayvision_katana/constants.py
rayvision_katana/katana_analyse_script.py
rayvision_katana/tests/__init__.py
rayvision_katana/tests/conftest.py
rayvision_katana/tests/test_analyze_katana.py
rayvision_katana-1.2.1.dist-info/METADATA
rayvision_katana-1.2.1.dist-info/WHEEL
rayvision_katana-1.2.1.dist-info/top_level.txt
rayvision_katana-1.2.1.dist-info/RECORD
